kubevim_vivnfm_client/__init__.py
kubevim_vivnfm_client/api_client.py
kubevim_vivnfm_client/api_response.py
kubevim_vivnfm_client/configuration.py
kubevim_vivnfm_client/exceptions.py
kubevim_vivnfm_client/py.typed
kubevim_vivnfm_client/rest.py
kubevim_vivnfm_client/api/__init__.py
kubevim_vivnfm_client/api/vi_vnfm_api.py
kubevim_vivnfm_client/models/__init__.py
kubevim_vivnfm_client/models/affinity_or_anti_affinity_constraint_for_compute.py
kubevim_vivnfm_client/models/affinity_or_anti_affinity_constraint_for_compute_affinity_or_anti_affinity_resource_list.py
kubevim_vivnfm_client/models/affinity_or_anti_affinity_constraint_for_compute_scope_of_affinity_or_anti_affinity_constraint_for_compute.py
kubevim_vivnfm_client/models/certificate_data.py
kubevim_vivnfm_client/models/compute_running_state.py
kubevim_vivnfm_client/models/filter.py
kubevim_vivnfm_client/models/identifier.py
kubevim_vivnfm_client/models/ip_address.py
kubevim_vivnfm_client/models/ip_address_pool.py
kubevim_vivnfm_client/models/ip_subnet_cidr.py
kubevim_vivnfm_client/models/ip_version.py
kubevim_vivnfm_client/models/mac_address.py
kubevim_vivnfm_client/models/metadata.py
kubevim_vivnfm_client/models/network_qo_s.py
kubevim_vivnfm_client/models/network_resource_type.py
kubevim_vivnfm_client/models/network_subnet.py
kubevim_vivnfm_client/models/network_subnet_data.py
kubevim_vivnfm_client/models/network_type.py
kubevim_vivnfm_client/models/operational_state.py
kubevim_vivnfm_client/models/pb_allocate_compute_request.py
kubevim_vivnfm_client/models/pb_allocate_compute_response.py
kubevim_vivnfm_client/models/pb_allocate_network_request.py
kubevim_vivnfm_client/models/pb_allocate_network_response.py
kubevim_vivnfm_client/models/pb_create_compute_flavour_request.py
kubevim_vivnfm_client/models/pb_create_compute_flavour_response.py
kubevim_vivnfm_client/models/pb_create_compute_resource_affinity_or_anti_affinity_constraints_group_request.py
kubevim_vivnfm_client-0.0.4.dist-info/licenses/LICENSE
kubevim_vivnfm_client-0.0.4.dist-info/METADATA
kubevim_vivnfm_client-0.0.4.dist-info/WHEEL
kubevim_vivnfm_client-0.0.4.dist-info/top_level.txt
kubevim_vivnfm_client-0.0.4.dist-info/RECORD
