Metadata-Version: 2.4
Name: kubevim-vivnfm-client
Version: 0.0.4
Summary: Python client for KubeVIM VI-VNFM API
Home-page: https://github.com/kube-nfv/kube-vim-api
Author: Dmytro Malovanyi
Author-email: dmitrymalovanyy@gmail.com
License: Apache-2.0
Keywords: OpenAPI,OpenAPI-Generator,vi-vnfm.proto
Classifier: Programming Language :: Python :: 3
Classifier: License :: OSI Approved :: Apache Software License
Classifier: Operating System :: OS Independent
License-File: LICENSE
Requires-Dist: urllib3<3.0.0,>=1.25.3
Requires-Dist: python-dateutil>=2.8.2
Requires-Dist: pydantic>=2
Requires-Dist: typing-extensions>=4.7.1
Dynamic: author
Dynamic: author-email
Dynamic: classifier
Dynamic: description
Dynamic: description-content-type
Dynamic: home-page
Dynamic: keywords
Dynamic: license
Dynamic: license-file
Dynamic: requires-dist
Dynamic: summary
